[
    {
        "pk": 65,
        "model": "products.product",
        "fields": {
            "category": 4,
            "brand": "Sony",
            "series": "PlayStation",
            "model": "4",
            "color": "black",
            "acceptable": true,
            "good": true,
            "excellent": true,
            "price": 249,
            "sale": false,
            "sale_price": null,
            "image": "ps4fat.jpg",
            "image_url": null
        }
    },
    {
        "pk": 65,
        "model": "products.console",
        "fields": {
            "storage_size": "500 GB"
        }
    },
    {
        "pk": 66,
        "model": "products.product",
        "fields": {
            "category": 4,
            "brand": "Sony",
            "series": "PlayStation",
            "model": "4 Slim",
            "color": "black",
            "acceptable": true,
            "good": true,
            "excellent": true,
            "price": 299,
            "sale": false,
            "sale_price": null,
            "image": "ps4slim.jpg",
            "image_url": null
        }
    },
    {
        "pk": 66,
        "model": "products.console",
        "fields": {
            "storage_size": "500 GB"
        }
    },
    {
        "pk": 67,
        "model": "products.product",
        "fields": {
            "category": 4,
            "brand": "Sony",
            "series": "PlayStation",
            "model": "4 Pro",
            "color": "black",
            "acceptable": true,
            "good": true,
            "excellent": true,
            "price": 349,
            "sale": false,
            "sale_price": null,
            "image": "ps4pro.jpg",
            "image_url": null
        }
    },
    {
        "pk": 67,
        "model": "products.console",
        "fields": {
            "storage_size": "1 TB"
        }
    },
    {
        "pk": 68,
        "model": "products.product",
        "fields": {
            "category": 4,
            "brand": "Sony",
            "series": "PlayStation",
            "model": "5 (digital edition)",
            "color": "white",
            "acceptable": true,
            "good": true,
            "excellent": true,
            "price": 379,
            "sale": false,
            "sale_price": null,
            "image": "ps5digital.jpg",
            "image_url": null
        }
    },
    {
        "pk": 68,
        "model": "products.console",
        "fields": {
            "storage_size": "1 TB"
        }
    },
    {
        "pk": 69,
        "model": "products.product",
        "fields": {
            "category": 4,
            "brand": "Sony",
            "series": "PlayStation",
            "model": "5",
            "color": "white",
            "acceptable": true,
            "good": true,
            "excellent": true,
            "price": 479,
            "sale": false,
            "sale_price": null,
            "image": "ps5.jpg",
            "image_url": null
        }
    },
    {
        "pk": 69,
        "model": "products.console",
        "fields": {
            "storage_size": "1 TB"
        }
    },
    {
        "pk": 70,
        "model": "products.product",
        "fields": {
            "category": 4,
            "brand": "Microsoft",
            "series": "Xbox",
            "model": "One",
            "color": "black",
            "acceptable": true,
            "good": true,
            "excellent": true,
            "price": 229,
            "sale": false,
            "sale_price": null,
            "image": "xboxone.jpg",
            "image_url": null
        }
    },
    {
        "pk": 70,
        "model": "products.console",
        "fields": {
            "storage_size": "500 GB"
        }

    },
    {
        "pk": 71,
        "model": "products.product",
        "fields": {
            "category": 4,
            "brand": "Microsoft",
            "series": "Xbox",
            "model": "One S",
            "color": "white",
            "acceptable": true,
            "good": true,
            "excellent": true,
            "price": 249,
            "sale": false,
            "sale_price": null,
            "image": "xboxones.jpg",
            "image_url": null
        }
    },
    {
        "pk": 71,
        "model": "products.console",
        "fields": {
            "storage_size": "500 GB"
        }
    },
    {
        "pk": 72,
        "model": "products.product",
        "fields": {
            "category": 4,
            "brand": "Microsoft",
            "series": "Xbox",
            "model": "One X",
            "color": "black",
            "acceptable": true,
            "good": true,
            "excellent": true,
            "price": 299,
            "sale": false,
            "sale_price": null,
            "image": "xboxonex.jpg",
            "image_url": null
        }
    },
    {
        "pk": 72,
        "model": "products.console",
        "fields": {
            "storage_size": "500 GB"
        }
    },
    {
        "pk": 73,
        "model": "products.product",
        "fields": {
            "category": 4,
            "brand": "Microsoft",
            "series": "Xbox",
            "model": "Series S",
            "color": "white",
            "acceptable": true,
            "good": true,
            "excellent": true,
            "price": 279,
            "sale": false,
            "sale_price": null,
            "image": "xboxseriess.jpg",
            "image_url": null
        }
    },
    {
        "pk": 73,
        "model": "products.console",
        "fields": {
            "storage_size": "500 GB"
        }
    },
    {
        "pk": 74,
        "model": "products.product",
        "fields": {
            "category": 4,
            "brand": "Microsoft",
            "series": "Xbox",
            "model": "Series X",
            "color": "black",
            "acceptable": true,
            "good": true,
            "excellent": true,
            "price": 479,
            "sale": false,
            "sale_price": null,
            "image": "xboxseriesx.jpg",
            "image_url": null
        }
    },
    {
        "pk": 74,
        "model": "products.console",
        "fields": {
            "storage_size": "1 TB"
        }
    },
    {
        "pk": 75,
        "model": "products.product",
        "fields": {
            "category": 4,
            "brand": "Nintendo",
            "series": "Switch",
            "model": "(standard)",
            "color": "black",
            "acceptable": true,
            "good": true,
            "excellent": true,
            "price": 299,
            "sale": false,
            "sale_price": null,
            "image": "nintendoswitch.jpg",
            "image_url": null
        }
    },
    {
        "pk": 75,
        "model": "products.console",
        "fields": {
            "storage_size": "32 GB"
        }
    },
    {
        "pk": 76,
        "model": "products.product",
        "fields": {
            "category": 4,
            "brand": "Nintendo",
            "series": "Switch",
            "model": "Lite",
            "color": "blue",
            "acceptable": true,
            "good": true,
            "excellent": true,
            "price": 199,
            "sale": false,
            "sale_price": null,
            "image": "nintendoswitchlite.jpg",
            "image_url": null
        }
    },
    {
        "pk": 76,
        "model": "products.console",
        "fields": {
            "storage_size": "32 GB"
        }
    },
    {
        "pk": 77,
        "model": "products.product",
        "fields": {
            "category": 4,
            "brand": "Nintendo",
            "series": "Switch",
            "model": "Oled",
            "color": "white",
            "acceptable": true,
            "good": true,
            "excellent": true,
            "price": 349,
            "sale": false,
            "sale_price": null,
            "image": "nintendoswitcholed.jpg",
            "image_url": null
        }
    },
    {
        "pk": 77,
        "model": "products.console",
        "fields": {
            "storage_size": "64 GB"
        }
    }

]